Metadata-Version: 2.1
Name: sphinx-plot-directive
Version: 1.0.3
Summary: "A .. plot::" directive for plotting figures in a Sphinx document.
Home-page: https://github.com/guoyoooping/sphinx-plot-directive
Author: Yongping Guo
Author-email: guoyoooping@163.com
License: MIT
Platform: UNKNOWN
Classifier: Programming Language :: Python :: 3
Classifier: License :: OSI Approved :: MIT License
Classifier: Operating System :: OS Independent
Requires-Python: >=3.7
License-File: LICENSE
